causalvis/__init__.py
causalvis/_version.py
causalvis/example.py
causalvis/widget.py
causalvis/labextension/package.json
causalvis/labextension/static/122.fd774fc52b80d43225cb.js
causalvis/labextension/static/158.d9d19b685fcde0decc22.js
causalvis/labextension/static/162.026473e5a953cdfec548.js
causalvis/labextension/static/171.cb4645c239308030578d.js
causalvis/labextension/static/2.721a1a01d635ce1ea169.js
causalvis/labextension/static/245.fa5be1c82c67cffebe26.js
causalvis/labextension/static/245.fa5be1c82c67cffebe26.js.LICENSE.txt
causalvis/labextension/static/254.47feedb449e4022a9397.js
causalvis/labextension/static/261.95ba221f33d28356e50d.js
causalvis/labextension/static/282.c17f72e88f7d535bd86d.js
causalvis/labextension/static/338.8c87477b19a5160d4b32.js
causalvis/labextension/static/338.8c87477b19a5160d4b32.js.LICENSE.txt
causalvis/labextension/static/378.e282d91b84d4a886da62.js
causalvis/labextension/static/391.2e5dca47acf656007dc6.js
causalvis/labextension/static/8.01575e88583b65bd3c1a.js
causalvis/labextension/static/846.203bdc18984325073463.js
causalvis/labextension/static/885.2fc691a1ae21d2a2f8c3.js
causalvis/labextension/static/890.6a82c7f1ee3d830fd269.js
causalvis/labextension/static/remoteEntry.a6816730a9660de4ac8e.js
causalvis/labextension/static/style.js
causalvis/labextension/static/third-party-licenses.json
causalvis/nbextension/extension.js
causalvis/nbextension/index.js
causalvis/nbextension/index.js.LICENSE.txt
causalvis-0.1.1a2.data/data/etc/jupyter/nbconfig/notebook.d/causalvis.json
causalvis-0.1.1a2.data/data/share/jupyter/labextensions/causalvis/install.json
causalvis-0.1.1a2.data/data/share/jupyter/labextensions/causalvis/package.json
causalvis-0.1.1a2.data/data/share/jupyter/labextensions/causalvis/static/122.fd774fc52b80d43225cb.js
causalvis-0.1.1a2.data/data/share/jupyter/labextensions/causalvis/static/158.d9d19b685fcde0decc22.js
causalvis-0.1.1a2.data/data/share/jupyter/labextensions/causalvis/static/162.026473e5a953cdfec548.js
causalvis-0.1.1a2.dist-info/METADATA
causalvis-0.1.1a2.dist-info/WHEEL
causalvis-0.1.1a2.dist-info/top_level.txt
causalvis-0.1.1a2.dist-info/RECORD
